<?xml version="1.0" encoding="utf-8"?>
<cms.classpermission>
  <ClassID>
    <CodeName>DancingGoatMvc.Coffee</CodeName>
    <GUID>74708f6d-5985-4b60-839d-aa2a8df0bc72</GUID>
    <ObjectType>cms.documenttype</ObjectType>
  </ClassID>
  <PermissionDescription>{$permissiondescription.document.create$}</PermissionDescription>
  <PermissionDisplayInMatrix>True</PermissionDisplayInMatrix>
  <PermissionDisplayName>{$permissionnames.create$}</PermissionDisplayName>
  <PermissionGUID>36616585-4565-4253-96de-49247cacb4de</PermissionGUID>
  <PermissionName>CreateSpecific</PermissionName>
  <PermissionOrder>3</PermissionOrder>
</cms.classpermission>