<?xml version="1.0" encoding="utf-8"?>
<cms.classpermission>
  <ClassID>
    <CodeName>DancingGoatMvc.HotTips</CodeName>
    <GUID>d62106bc-6acc-4122-ab3f-97ea4faa08a7</GUID>
    <ObjectType>cms.documenttype</ObjectType>
  </ClassID>
  <PermissionDescription>{$permissiondescription.document.modify$}</PermissionDescription>
  <PermissionDisplayInMatrix>True</PermissionDisplayInMatrix>
  <PermissionDisplayName>{$permissionnames.modify$}</PermissionDisplayName>
  <PermissionGUID>1f8ee412-3236-4d7d-a759-b80446d1cd90</PermissionGUID>
  <PermissionName>Modify</PermissionName>
  <PermissionOrder>2</PermissionOrder>
</cms.classpermission>