<?xml version="1.0" encoding="utf-8"?>
<cms.classpermission>
  <ClassID>
    <CodeName>DancingGoatMvc.Generator</CodeName>
    <GUID>28e81a0b-188f-4fe6-974a-c248c58d6713</GUID>
    <ObjectType>cms.documenttype</ObjectType>
  </ClassID>
  <PermissionDescription>{$permissiondescription.document.create$}</PermissionDescription>
  <PermissionDisplayInMatrix>True</PermissionDisplayInMatrix>
  <PermissionDisplayName>{$permissionnames.create$}</PermissionDisplayName>
  <PermissionGUID>35e9c20c-01d1-4e52-843a-d9fcbe66eacb</PermissionGUID>
  <PermissionName>CreateSpecific</PermissionName>
  <PermissionOrder>3</PermissionOrder>
</cms.classpermission>